bitbot.py
music.py
speech.py
mbitutils-0.0.4.dist-info/LICENSE.txt
mbitutils-0.0.4.dist-info/METADATA
mbitutils-0.0.4.dist-info/WHEEL
mbitutils-0.0.4.dist-info/top_level.txt
mbitutils-0.0.4.dist-info/RECORD
