Metadata-Version: 2.1
Name: mbitutils
Version: 0.0.4
Summary: A Python module for the 4tronix Bit:bot XL and stubs for the BBC micro:bit.
Home-page: https://github.com/oivron/mbitutils
Author: Øivind Rønning, Statped
Author-email: oiron@statped.no
License: GNU GENERAL PUBLIC LICENSE
Project-URL: Source, https://github.com/oivron/mbitutils
Keywords: micro:bit Bit:bot
Platform: UNKNOWN
Classifier: Development Status :: 3 - Alpha
Classifier: Intended Audience :: Education
Classifier: Operating System :: Microsoft :: Windows :: Windows 10
Classifier: Programming Language :: Python :: 3
Classifier: License :: OSI Approved :: MIT License
Requires-Python: >=3
Requires-Dist: uflash
Requires-Dist: microfs
Requires-Dist: pylint
